rtl/ex_mem_reg.v
// Description: EX/MEM pipeline register

module ex_mem_reg (
    input wire clk,
    input wire rst,
    input wire [31:0] pc_in,
    input wire [31:0] alu_result_in,
    input wire [2:0] funct3_in,
    input wire [31:0] rs2_data_in,
    input wire [31:0] branch_target_in,
    input wire [31:0] jump_target_in,
    input wire [4:0] rd_in,
    input wire [4:0] rs1_in,
    input wire [4:0] rs2_in,
    input wire [1:0] wb_sel_in,
    input wire mem_read_in,
    input wire mem_write_in,
    input wire reg_write_in,
    input wire mem_to_reg_in,
    input wire branch_taken_in,
    input wire jump_in,

    output reg [31:0] pc_out,
    output reg [31:0] alu_result_out,
    output reg [2:0] funct3_out,
    output reg [31:0] rs2_data_out,
    output reg [4:0] rs1_out,
    output reg [4:0] rs2_out,
    output reg [4:0] rd_out,
    output reg [31:0] branch_target_out,
    output reg [31:0] jump_target_out,
    output reg [1:0] wb_sel_out,
    output reg mem_read_out,
    output reg mem_write_out,
    output reg reg_write_out,
    output reg mem_to_reg_out,
    output reg branch_taken_out,
    output reg jump_out

);

always @(posedge clk or posedge rst) begin
    if (rst) begin
        pc_out <= 32'b0;
        alu_result_out <= 32'b0;
        funct3_out <= 3'b0;
        rs2_data_out <= 32'b0;
        rd_out <= 5'b0;
        rs1_out <= 5'b0;
        rs2_out <= 5'b0;
        branch_target_out <= 32'b0;
        jump_target_out <= 32'b0;
        wb_sel_out <= 2'b0;
        mem_read_out <= 1'b0;
        mem_write_out <= 1'b0;
        reg_write_out <= 1'b0;
        mem_to_reg_out <= 1'b0;
        branch_taken_out <= 1'b0;
        jump_out <= 1'b0;
    end else begin
        pc_out <= pc_in;
        alu_result_out <= alu_result_in;
        funct3_out <= funct3_in;
        rs2_data_out <= rs2_data_in;
        rd_out <= rd_in;
        rs1_out <= rs1_in;
        rs2_out <= rs2_in;
        branch_target_out <= branch_target_in;
        jump_target_out <= jump_target_in;
        wb_sel_out <= wb_sel_in;
        mem_read_out <= mem_read_in;
        mem_write_out <= mem_write_in;
        reg_write_out <= reg_write_in;
        mem_to_reg_out <= mem_to_reg_in;
        branch_taken_out <= branch_taken_in;
        jump_out <= jump_in;
    end
end

endmodule

rtl/jump_unit.v
module jump_unit(
    input wire [31:0] pc,
    input wire [31:0] rs1_data,
    input wire [31:0] imm,
    input wire jal,
    input wire jalr,
    output reg jump,
    output reg [31:0] jump_target

);

always @(*) begin
    jump = 1'b0;
    jump_target = 32'b0;

    if (jal) begin
        jump = 1'b1;
        jump_target = pc + imm;
    end else if (jalr) begin 
        jump = 1'b1;
        jump_target = (rs1_data + imm) & 32'hFFFFFFFE;
    end
end

endmodule

rtl/branch_unit.v
// Description: Branch Logic Module for RV32I core
// Supports signed and unsigned instructions (BEQ,BNE,BLT,BGE,BLTU,BGEU)

module branch_unit (
    input wire [31:0] op_A,
    input wire [31:0] op_B,
    input wire [2:0] branch_ctrl,
    input wire [31:0] imm,
    input wire [31:0] pc,
    input wire branch,
    input wire zero_flag,      // used by BEQ and BNE for branch_taken signal
    output reg branch_taken,
    output reg [31:0] branch_target
);

localparam BEQ = 3'b000;  // Branch if equal
localparam BNE = 3'b001;  // Branch if not equal
localparam BLT = 3'b010;  // Branch if less than
localparam BGE = 3'b011;  // Branch if greater than or equal
localparam BLTU = 3'b100; // Branch if less than unsigned
localparam BGEU = 3'b101; // Branch if greater than or equal unsigned

    always @(*) begin
        branch_taken = 1'b0;
        branch_target = 32'b0;

         if (branch) begin 
            branch_target = pc + imm;
            case (branch_ctrl)
                BEQ: branch_taken = zero_flag; 
                BNE: branch_taken = !zero_flag;  
                BLT: branch_taken = ($signed(op_A) < $signed(op_B));  // signed
                BGE: branch_taken = ($signed(op_A) >= $signed(op_B)); // signed
                BLTU: branch_taken = (op_A < op_B);  // unsigned
                BGEU: branch_taken = (op_A >= op_B); // unsigned
                default: branch_taken = 1'b0;        
            endcase
         end

end
    
endmodule

rtl/alu.v
module alu (
    input wire [31:0] op_A,
    input wire [31:0] op_B,
    input wire [3:0] alu_ctrl,
    output reg [31:0] alu_result,
    output wire zero_flag

);
localparam ADD = 4'b0000;
localparam SUB = 4'b0001;
localparam AND = 4'b0010;
localparam OR  = 4'b0011;
localparam XOR = 4'b0100;
localparam SLL = 4'b0101;
localparam SRL = 4'b0110;
localparam SRA = 4'b0111;
localparam SLT = 4'b1000;
localparam SLTU = 4'b1001;
localparam PASS = 4'b1010;
localparam ADD_PC = 4'b1011; // Add pc for AUIPC instruction

always @(*) begin
    case (alu_ctrl)
        ADD: alu_result = op_A + op_B;        
        SUB: alu_result = op_A - op_B;      
        AND: alu_result = op_A & op_B;        
        OR: alu_result = op_A | op_B;       
        XOR: alu_result = op_A ^ op_B;        
        SLL: alu_result = op_A << op_B[4:0]; 
        SRL: alu_result = op_A >> op_B[4:0];  
        SRA: alu_result = $signed(op_A) >>> op_B[4:0];    
        SLT: alu_result = ($signed(op_A) < $signed(op_B)) ? 32'b1 : 32'b0;  
        SLTU: alu_result = (op_A < op_B) ? 32'b1 : 32'b0; 
        PASS: alu_result = op_B;
        ADD_PC: alu_result = op_A + op_B; // For AUIPC, add immediate to PC
        default: alu_result = 32'b0;                        
    endcase
end

assign zero_flag = (alu_result == 32'b0) ? 1'b1 : 1'b0;
    
endmodule

rtl/ex_stage_pip.v
module ex_stage_pip (
    input wire clk,
    input wire rst,
    input wire [31:0] pc_in,
    input wire [31:0] rs1_data_in,
    input wire [31:0] rs2_data_in,
    input wire [2:0] funct3_in,
    input wire [31:0] imm_in,
    input wire [4:0] rs1_in,
    input wire [4:0] rs2_in,
    input wire [4:0] rd_in,
    input wire [3:0] alu_ctrl_in,
    input wire [2:0] branch_ctrl_in,
    input wire [1:0] wb_sel_in,
    input wire reg_write_in,
    input wire mem_read_in,
    input wire mem_write_in,
    input wire mem_to_reg_in,
    input wire alu_src_in,
    input wire branch_in,
    input wire jal_in,
    input wire jalr_in,

    // input from forwarding unit
    input wire [1:0] forward_rs1,
    input wire [1:0] forward_rs2,
    input wire [31:0] forward_data_mem,
    input wire [31:0] forward_data_wb,

    output wire [31:0] pc_out,
    output wire [2:0] funct3_out,
    output wire [31:0] alu_result_out,
    output wire [31:0] rs2_data_out,
    output wire [4:0] rd_out,
    output wire [4:0] rs1_out,
    output wire [4:0] rs2_out,
    output wire [31:0] branch_target_out,
    output wire [31:0] jump_target_out,
    output wire [1:0] wb_sel_out,
    output wire mem_read_out,
    output wire mem_write_out,
    output wire reg_write_out,
    output wire mem_to_reg_out,
    output wire branch_taken_out,
    output wire jump_out,

    //debug
    output wire [31:0] alu_a_debug, 
    output wire [31:0] alu_b_debug,
    output wire [3:0] alu_ctrl_debug
    
    
);

wire [31:0] rs1_data, rs2_data;
wire [31:0] alu_A, alu_B;
wire [31:0] alu_result;
wire zero_flag;

// mux logic for rs1 and rs2 data selection based on forwarding
 assign rs1_data = (forward_rs1 == 2'b00) ? rs1_data_in:
                   (forward_rs1 == 2'b10) ? forward_data_mem:
                   (forward_rs1 == 2'b01) ? forward_data_wb : rs1_data_in;

assign rs2_data = (forward_rs2 == 2'b00) ? rs2_data_in:
                   (forward_rs2 == 2'b10) ? forward_data_mem:
                   (forward_rs2 == 2'b01) ? forward_data_wb : rs1_data_in;

assign alu_A = (alu_ctrl_in == 4'b1011) ? pc_in : rs1_data;
assign alu_B = alu_src_in ? imm_in : rs2_data; // select between immediate or rs2 data

assign alu_a_debug = alu_A;
assign alu_b_debug = alu_B;
assign alu_ctrl_debug = alu_ctrl_in;


alu alu_unit (
    .op_A(alu_A),
    .op_B(alu_B),
    .alu_ctrl(alu_ctrl_in),
    .alu_result(alu_result),
    .zero_flag(zero_flag)
);

wire branch_taken;
wire [31:0] branch_target;

branch_unit brch_unit(
    .op_A(rs1_data),
    .op_B(rs2_data),
    .branch_ctrl(branch_ctrl_in),
    .imm(imm_in),
    .pc(pc_in),
    .branch(branch_in),
    .zero_flag(zero_flag),
    .branch_taken(branch_taken),
    .branch_target(branch_target)
);

wire jump;
wire [31:0] jump_target;

jump_unit jmp_unit(
    .pc(pc_in),
    .rs1_data(rs1_data),
    .imm(imm_in),
    .jal(jal_in),
    .jalr(jalr_in),
    .jump(jump),
    .jump_target(jump_target)
);

ex_mem_reg exmem_register (
    .clk(clk),
    .rst(rst),
    .pc_in(pc_in),
    .alu_result_in(alu_result),
    .funct3_in(funct3_in),
    .rs2_data_in(rs2_data),
    .branch_target_in(branch_target),  
    .jump_target_in(jump_target),
    .rd_in(rd_in),
    .rs1_in(rs1_in),
    .rs2_in(rs2_in),
    .wb_sel_in(wb_sel_in),
    .mem_read_in(mem_read_in),
    .mem_write_in(mem_write_in),
    .reg_write_in(reg_write_in),
    .mem_to_reg_in(mem_to_reg_in),
    .branch_taken_in(branch_taken),
    .jump_in(jump),
    .pc_out(pc_out),
    .alu_result_out(alu_result_out),
    .rs2_data_out(rs2_data_out),
    .funct3_out(funct3_out),
    .rd_out(rd_out),
    .rs1_out(rs1_out),
    .rs2_out(rs2_out),
    .branch_target_out(branch_target_out),
    .jump_target_out(jump_target_out),
    .wb_sel_out(wb_sel_out),
    .mem_read_out(mem_read_out),
    .mem_write_out(mem_write_out),
    .reg_write_out(reg_write_out),
    .mem_to_reg_out(mem_to_reg_out),
    .branch_taken_out(branch_taken_out),
    .jump_out(jump_out)

);


endmodule

vcd/ex_stage.vcd
$version Generated by VerilatedVcd $end
$timescale 1ps $end
 $scope module TOP $end
  $var wire 1 # clk $end
  $var wire 1 $ rst $end
  $var wire 32 % pc_in [31:0] $end
  $var wire 32 & rs1_data_in [31:0] $end
  $var wire 32 ' rs2_data_in [31:0] $end
  $var wire 3 ( funct3_in [2:0] $end
  $var wire 32 ) imm_in [31:0] $end
  $var wire 5 * rs1_in [4:0] $end
  $var wire 5 + rs2_in [4:0] $end
  $var wire 5 , rd_in [4:0] $end
  $var wire 4 - alu_ctrl_in [3:0] $end
  $var wire 3 . branch_ctrl_in [2:0] $end
  $var wire 2 / wb_sel_in [1:0] $end
  $var wire 1 0 reg_write_in $end
  $var wire 1 1 mem_read_in $end
  $var wire 1 2 mem_write_in $end
  $var wire 1 3 mem_to_reg_in $end
  $var wire 1 4 alu_src_in $end
  $var wire 1 5 branch_in $end
  $var wire 1 6 jal_in $end
  $var wire 1 7 jalr_in $end
  $var wire 2 8 forward_rs1 [1:0] $end
  $var wire 2 9 forward_rs2 [1:0] $end
  $var wire 32 : forward_data_mem [31:0] $end
  $var wire 32 ; forward_data_wb [31:0] $end
  $var wire 32 < pc_out [31:0] $end
  $var wire 3 = funct3_out [2:0] $end
  $var wire 32 > alu_result_out [31:0] $end
  $var wire 32 ? rs2_data_out [31:0] $end
  $var wire 5 @ rd_out [4:0] $end
  $var wire 5 A rs1_out [4:0] $end
  $var wire 5 B rs2_out [4:0] $end
  $var wire 32 C branch_target_out [31:0] $end
  $var wire 32 D jump_target_out [31:0] $end
  $var wire 2 E wb_sel_out [1:0] $end
  $var wire 1 F mem_read_out $end
  $var wire 1 G mem_write_out $end
  $var wire 1 H reg_write_out $end
  $var wire 1 I mem_to_reg_out $end
  $var wire 1 J branch_taken_out $end
  $var wire 1 K jump_out $end
  $var wire 32 L alu_a_debug [31:0] $end
  $var wire 32 M alu_b_debug [31:0] $end
  $var wire 4 N alu_ctrl_debug [3:0] $end
  $scope module ex_stage_pip $end
   $var wire 1 O clk $end
   $var wire 1 P rst $end
   $var wire 32 Q pc_in [31:0] $end
   $var wire 32 R rs1_data_in [31:0] $end
   $var wire 32 S rs2_data_in [31:0] $end
   $var wire 3 T funct3_in [2:0] $end
   $var wire 32 U imm_in [31:0] $end
   $var wire 5 V rs1_in [4:0] $end
   $var wire 5 W rs2_in [4:0] $end
   $var wire 5 X rd_in [4:0] $end
   $var wire 4 Y alu_ctrl_in [3:0] $end
   $var wire 3 Z branch_ctrl_in [2:0] $end
   $var wire 2 [ wb_sel_in [1:0] $end
   $var wire 1 \ reg_write_in $end
   $var wire 1 ] mem_read_in $end
   $var wire 1 ^ mem_write_in $end
   $var wire 1 _ mem_to_reg_in $end
   $var wire 1 ` alu_src_in $end
   $var wire 1 a branch_in $end
   $var wire 1 b jal_in $end
   $var wire 1 c jalr_in $end
   $var wire 2 d forward_rs1 [1:0] $end
   $var wire 2 e forward_rs2 [1:0] $end
   $var wire 32 f forward_data_mem [31:0] $end
   $var wire 32 g forward_data_wb [31:0] $end
   $var wire 32 h pc_out [31:0] $end
   $var wire 3 i funct3_out [2:0] $end
   $var wire 32 j alu_result_out [31:0] $end
   $var wire 32 k rs2_data_out [31:0] $end
   $var wire 5 l rd_out [4:0] $end
   $var wire 5 m rs1_out [4:0] $end
   $var wire 5 n rs2_out [4:0] $end
   $var wire 32 o branch_target_out [31:0] $end
   $var wire 32 p jump_target_out [31:0] $end
   $var wire 2 q wb_sel_out [1:0] $end
   $var wire 1 r mem_read_out $end
   $var wire 1 s mem_write_out $end
   $var wire 1 t reg_write_out $end
   $var wire 1 u mem_to_reg_out $end
   $var wire 1 v branch_taken_out $end
   $var wire 1 w jump_out $end
   $var wire 32 x alu_a_debug [31:0] $end
   $var wire 32 y alu_b_debug [31:0] $end
   $var wire 4 z alu_ctrl_debug [3:0] $end
   $var wire 32 { rs1_data [31:0] $end
   $var wire 32 | rs2_data [31:0] $end
   $var wire 32 } alu_A [31:0] $end
   $var wire 32 ~ alu_B [31:0] $end
   $var wire 32 !! alu_result [31:0] $end
   $var wire 1 "! zero_flag $end
   $var wire 1 #! branch_taken $end
   $var wire 32 $! branch_target [31:0] $end
   $var wire 1 %! jump $end
   $var wire 32 &! jump_target [31:0] $end
   $scope module alu_unit $end
    $var wire 32 '! op_A [31:0] $end
    $var wire 32 (! op_B [31:0] $end
    $var wire 4 )! alu_ctrl [3:0] $end
    $var wire 32 *! alu_result [31:0] $end
    $var wire 1 +! zero_flag $end
    $var wire 4 ^! ADD [3:0] $end
    $var wire 4 _! SUB [3:0] $end
    $var wire 4 `! AND [3:0] $end
    $var wire 4 a! OR [3:0] $end
    $var wire 4 b! XOR [3:0] $end
    $var wire 4 c! SLL [3:0] $end
    $var wire 4 d! SRL [3:0] $end
    $var wire 4 e! SRA [3:0] $end
    $var wire 4 f! SLT [3:0] $end
    $var wire 4 g! SLTU [3:0] $end
    $var wire 4 h! PASS [3:0] $end
    $var wire 4 i! ADD_PC [3:0] $end
   $upscope $end
   $scope module brch_unit $end
    $var wire 32 ,! op_A [31:0] $end
    $var wire 32 -! op_B [31:0] $end
    $var wire 3 .! branch_ctrl [2:0] $end
    $var wire 32 /! imm [31:0] $end
    $var wire 32 0! pc [31:0] $end
    $var wire 1 1! branch $end
    $var wire 1 2! zero_flag $end
    $var wire 1 3! branch_taken $end
    $var wire 32 4! branch_target [31:0] $end
    $var wire 3 j! BEQ [2:0] $end
    $var wire 3 k! BNE [2:0] $end
    $var wire 3 l! BLT [2:0] $end
    $var wire 3 m! BGE [2:0] $end
    $var wire 3 n! BLTU [2:0] $end
    $var wire 3 o! BGEU [2:0] $end
   $upscope $end
   $scope module exmem_register $end
    $var wire 1 5! clk $end
    $var wire 1 6! rst $end
    $var wire 32 7! pc_in [31:0] $end
    $var wire 32 8! alu_result_in [31:0] $end
    $var wire 3 9! funct3_in [2:0] $end
    $var wire 32 :! rs2_data_in [31:0] $end
    $var wire 32 ;! branch_target_in [31:0] $end
    $var wire 32 <! jump_target_in [31:0] $end
    $var wire 5 =! rd_in [4:0] $end
    $var wire 5 >! rs1_in [4:0] $end
    $var wire 5 ?! rs2_in [4:0] $end
    $var wire 2 @! wb_sel_in [1:0] $end
    $var wire 1 A! mem_read_in $end
    $var wire 1 B! mem_write_in $end
    $var wire 1 C! reg_write_in $end
    $var wire 1 D! mem_to_reg_in $end
    $var wire 1 E! branch_taken_in $end
    $var wire 1 F! jump_in $end
    $var wire 32 G! pc_out [31:0] $end
    $var wire 32 H! alu_result_out [31:0] $end
    $var wire 3 I! funct3_out [2:0] $end
    $var wire 32 J! rs2_data_out [31:0] $end
    $var wire 5 K! rs1_out [4:0] $end
    $var wire 5 L! rs2_out [4:0] $end
    $var wire 5 M! rd_out [4:0] $end
    $var wire 32 N! branch_target_out [31:0] $end
    $var wire 32 O! jump_target_out [31:0] $end
    $var wire 2 P! wb_sel_out [1:0] $end
    $var wire 1 Q! mem_read_out $end
    $var wire 1 R! mem_write_out $end
    $var wire 1 S! reg_write_out $end
    $var wire 1 T! mem_to_reg_out $end
    $var wire 1 U! branch_taken_out $end
    $var wire 1 V! jump_out $end
   $upscope $end
   $scope module jmp_unit $end
    $var wire 32 W! pc [31:0] $end
    $var wire 32 X! rs1_data [31:0] $end
    $var wire 32 Y! imm [31:0] $end
    $var wire 1 Z! jal $end
    $var wire 1 [! jalr $end
    $var wire 1 \! jump $end
    $var wire 32 ]! jump_target [31:0] $end
   $upscope $end
  $upscope $end
 $upscope $end
$enddefinitions $end


#0
0#
1$
b00000000000000000000000000000000 %
b00000000000000000000000000000000 &
b00000000000000000000000000000000 '
b000 (
b00000000000000000000000000000000 )
b00000 *
b00000 +
b00000 ,
b0000 -
b000 .
b00 /
00
01
02
03
04
05
06
07
b00 8
b00 9
b00000000000000000000000000000000 :
b00000000000000000000000000000000 ;
b00000000000000000000000000000000 <
b000 =
b00000000000000000000000000000000 >
b00000000000000000000000000000000 ?
b00000 @
b00000 A
b00000 B
b00000000000000000000000000000000 C
b00000000000000000000000000000000 D
b00 E
0F
0G
0H
0I
0J
0K
b00000000000000000000000000000000 L
b00000000000000000000000000000000 M
b0000 N
0O
1P
b00000000000000000000000000000000 Q
b00000000000000000000000000000000 R
b00000000000000000000000000000000 S
b000 T
b00000000000000000000000000000000 U
b00000 V
b00000 W
b00000 X
b0000 Y
b000 Z
b00 [
0\
0]
0^
0_
0`
0a
0b
0c
b00 d
b00 e
b00000000000000000000000000000000 f
b00000000000000000000000000000000 g
b00000000000000000000000000000000 h
b000 i
b00000000000000000000000000000000 j
b00000000000000000000000000000000 k
b00000 l
b00000 m
b00000 n
b00000000000000000000000000000000 o
b00000000000000000000000000000000 p
b00 q
0r
0s
0t
0u
0v
0w
b00000000000000000000000000000000 x
b00000000000000000000000000000000 y
b0000 z
b00000000000000000000000000000000 {
b00000000000000000000000000000000 |
b00000000000000000000000000000000 }
b00000000000000000000000000000000 ~
b00000000000000000000000000000000 !!
1"!
0#!
b00000000000000000000000000000000 $!
0%!
b00000000000000000000000000000000 &!
b00000000000000000000000000000000 '!
b00000000000000000000000000000000 (!
b0000 )!
b00000000000000000000000000000000 *!
1+!
b00000000000000000000000000000000 ,!
b00000000000000000000000000000000 -!
b000 .!
b00000000000000000000000000000000 /!
b00000000000000000000000000000000 0!
01!
12!
03!
b00000000000000000000000000000000 4!
05!
16!
b00000000000000000000000000000000 7!
b00000000000000000000000000000000 8!
b000 9!
b00000000000000000000000000000000 :!
b00000000000000000000000000000000 ;!
b00000000000000000000000000000000 <!
b00000 =!
b00000 >!
b00000 ?!
b00 @!
0A!
0B!
0C!
0D!
0E!
0F!
b00000000000000000000000000000000 G!
b00000000000000000000000000000000 H!
b000 I!
b00000000000000000000000000000000 J!
b00000 K!
b00000 L!
b00000 M!
b00000000000000000000000000000000 N!
b00000000000000000000000000000000 O!
b00 P!
0Q!
0R!
0S!
0T!
0U!
0V!
b00000000000000000000000000000000 W!
b00000000000000000000000000000000 X!
b00000000000000000000000000000000 Y!
0Z!
0[!
0\!
b00000000000000000000000000000000 ]!
b0000 ^!
b0001 _!
b0010 `!
b0011 a!
b0100 b!
b0101 c!
b0110 d!
b0111 e!
b1000 f!
b1001 g!
b1010 h!
b1011 i!
b000 j!
b001 k!
b010 l!
b011 m!
b100 n!
b101 o!
#1
1#
1O
15!
#2
0#
0$
0O
0P
05!
06!
#3
1#
1O
15!
#4
0#
b00000000000000000000000000001010 &
b00000000000000000000000000001010 '
10
b00000000000000000000000000001010 L
b00000000000000000000000000001010 M
0O
b00000000000000000000000000001010 R
b00000000000000000000000000001010 S
1\
b00000000000000000000000000001010 x
b00000000000000000000000000001010 y
b00000000000000000000000000001010 {
b00000000000000000000000000001010 |
b00000000000000000000000000001010 }
b00000000000000000000000000001010 ~
b00000000000000000000000000010100 !!
0"!
b00000000000000000000000000001010 '!
b00000000000000000000000000001010 (!
b00000000000000000000000000010100 *!
0+!
b00000000000000000000000000001010 ,!
b00000000000000000000000000001010 -!
02!
05!
b00000000000000000000000000010100 8!
b00000000000000000000000000001010 :!
1C!
b00000000000000000000000000001010 X!
#5
1#
b00000000000000000000000000010100 >
b00000000000000000000000000001010 ?
1H
1O
b00000000000000000000000000010100 j
b00000000000000000000000000001010 k
1t
15!
b00000000000000000000000000010100 H!
b00000000000000000000000000001010 J!
1S!
#6
0#
b00000000000000000000000000000000 &
b00000000000000000000000000000101 '
b10 8
b00000000000000000000000000010100 :
b00000000000000000000000000010100 L
b00000000000000000000000000000101 M
0O
b00000000000000000000000000000000 R
b00000000000000000000000000000101 S
b10 d
b00000000000000000000000000010100 f
b00000000000000000000000000010100 x
b00000000000000000000000000000101 y
b00000000000000000000000000010100 {
b00000000000000000000000000000101 |
b00000000000000000000000000010100 }
b00000000000000000000000000000101 ~
b00000000000000000000000000011001 !!
b00000000000000000000000000010100 '!
b00000000000000000000000000000101 (!
b00000000000000000000000000011001 *!
b00000000000000000000000000010100 ,!
b00000000000000000000000000000101 -!
05!
b00000000000000000000000000011001 8!
b00000000000000000000000000000101 :!
b00000000000000000000000000010100 X!
#7
1#
b00000000000000000000000000011001 >
b00000000000000000000000000000101 ?
1O
b00000000000000000000000000011001 j
b00000000000000000000000000000101 k
15!
b00000000000000000000000000011001 H!
b00000000000000000000000000000101 J!
#8
0#
b00000000000000000000000000001010 &
b00000000000000000000000000000000 '
b00 8
b01 9
b00000000000000000000000000001100 ;
b00000000000000000000000000001010 L
b00000000000000000000000000001100 M
0O
b00000000000000000000000000001010 R
b00000000000000000000000000000000 S
b00 d
b01 e
b00000000000000000000000000001100 g
b00000000000000000000000000001010 x
b00000000000000000000000000001100 y
b00000000000000000000000000001010 {
b00000000000000000000000000001100 |
b00000000000000000000000000001010 }
b00000000000000000000000000001100 ~
b00000000000000000000000000010110 !!
b00000000000000000000000000001010 '!
b00000000000000000000000000001100 (!
b00000000000000000000000000010110 *!
b00000000000000000000000000001010 ,!
b00000000000000000000000000001100 -!
05!
b00000000000000000000000000010110 8!
b00000000000000000000000000001100 :!
b00000000000000000000000000001010 X!
#9
1#
b00000000000000000000000000010110 >
b00000000000000000000000000001100 ?
1O
b00000000000000000000000000010110 j
b00000000000000000000000000001100 k
15!
b00000000000000000000000000010110 H!
b00000000000000000000000000001100 J!
#10
0#
b00000000000000000000000000101010 &
b00000000000000000000000000101010 '
b00000000000000000000000000000100 )
b0001 -
15
b00 9
b00000000000000000000000000101010 L
b00000000000000000000000000101010 M
b0001 N
0O
b00000000000000000000000000101010 R
b00000000000000000000000000101010 S
b00000000000000000000000000000100 U
b0001 Y
1a
b00 e
b00000000000000000000000000101010 x
b00000000000000000000000000101010 y
b0001 z
b00000000000000000000000000101010 {
b00000000000000000000000000101010 |
b00000000000000000000000000101010 }
b00000000000000000000000000101010 ~
b00000000000000000000000000000000 !!
1"!
1#!
b00000000000000000000000000000100 $!
b00000000000000000000000000101010 '!
b00000000000000000000000000101010 (!
b0001 )!
b00000000000000000000000000000000 *!
1+!
b00000000000000000000000000101010 ,!
b00000000000000000000000000101010 -!
b00000000000000000000000000000100 /!
11!
12!
13!
b00000000000000000000000000000100 4!
05!
b00000000000000000000000000000000 8!
b00000000000000000000000000101010 :!
b00000000000000000000000000000100 ;!
1E!
b00000000000000000000000000101010 X!
b00000000000000000000000000000100 Y!
#11
1#
b00000000000000000000000000000000 >
b00000000000000000000000000101010 ?
b00000000000000000000000000000100 C
1J
1O
b00000000000000000000000000000000 j
b00000000000000000000000000101010 k
b00000000000000000000000000000100 o
1v
15!
b00000000000000000000000000000000 H!
b00000000000000000000000000101010 J!
b00000000000000000000000000000100 N!
1U!
#12
0#
b00000000000000000000000000001010 &
b00000000000000000000000000010100 '
b00000000000000000000000000001010 L
b00000000000000000000000000010100 M
0O
b00000000000000000000000000001010 R
b00000000000000000000000000010100 S
b00000000000000000000000000001010 x
b00000000000000000000000000010100 y
b00000000000000000000000000001010 {
b00000000000000000000000000010100 |
b00000000000000000000000000001010 }
b00000000000000000000000000010100 ~
b11111111111111111111111111110110 !!
0"!
0#!
b00000000000000000000000000001010 '!
b00000000000000000000000000010100 (!
b11111111111111111111111111110110 *!
0+!
b00000000000000000000000000001010 ,!
b00000000000000000000000000010100 -!
02!
03!
05!
b11111111111111111111111111110110 8!
b00000000000000000000000000010100 :!
0E!
b00000000000000000000000000001010 X!
#13
1#
b11111111111111111111111111110110 >
b00000000000000000000000000010100 ?
0J
1O
b11111111111111111111111111110110 j
b00000000000000000000000000010100 k
0v
15!
b11111111111111111111111111110110 H!
b00000000000000000000000000010100 J!
0U!
#14
0#
1$
b00000000000000000000000000000000 >
b00000000000000000000000000000000 ?
b00000000000000000000000000000000 C
0H
0O
1P
b00000000000000000000000000000000 j
b00000000000000000000000000000000 k
b00000000000000000000000000000000 o
0t
05!
16!
b00000000000000000000000000000000 H!
b00000000000000000000000000000000 J!
b00000000000000000000000000000000 N!
0S!
#15
1#
1O
15!
#16
0#
0$
0O
0P
05!
06!
#17
1#
b11111111111111111111111111110110 >
b00000000000000000000000000010100 ?
b00000000000000000000000000000100 C
1H
1O
b11111111111111111111111111110110 j
b00000000000000000000000000010100 k
b00000000000000000000000000000100 o
1t
15!
b11111111111111111111111111110110 H!
b00000000000000000000000000010100 J!
b00000000000000000000000000000100 N!
1S!
#18
0#
b00000000000000000000000000001000 %
b00000000000000000000000001100100 )
16
0O
b00000000000000000000000000001000 Q
b00000000000000000000000001100100 U
1b
b00000000000000000000000001101100 $!
1%!
b00000000000000000000000001101100 &!
b00000000000000000000000001100100 /!
b00000000000000000000000000001000 0!
b00000000000000000000000001101100 4!
05!
b00000000000000000000000000001000 7!
b00000000000000000000000001101100 ;!
b00000000000000000000000001101100 <!
1F!
b00000000000000000000000000001000 W!
b00000000000000000000000001100100 Y!
1Z!
1\!
b00000000000000000000000001101100 ]!
#19
1#
b00000000000000000000000000001000 <
b00000000000000000000000001101100 C
b00000000000000000000000001101100 D
1K
1O
b00000000000000000000000000001000 h
b00000000000000000000000001101100 o
b00000000000000000000000001101100 p
1w
15!
b00000000000000000000000000001000 G!
b00000000000000000000000001101100 N!
b00000000000000000000000001101100 O!
1V!
#20
0#
b00000000000000000000000000000000 &
b00000000000000000000000000000000 '
b0000 -
b10 8
b01 9
b00000000000000000000000000000101 ;
b00000000000000000000000000010100 L
b00000000000000000000000000000101 M
b0000 N
0O
b00000000000000000000000000000000 R
b00000000000000000000000000000000 S
b0000 Y
b10 d
b01 e
b00000000000000000000000000000101 g
b00000000000000000000000000010100 x
b00000000000000000000000000000101 y
b0000 z
b00000000000000000000000000010100 {
b00000000000000000000000000000101 |
b00000000000000000000000000010100 }
b00000000000000000000000000000101 ~
b00000000000000000000000000011001 !!
b00000000000000000000000000010100 '!
b00000000000000000000000000000101 (!
b0000 )!
b00000000000000000000000000011001 *!
b00000000000000000000000000010100 ,!
b00000000000000000000000000000101 -!
05!
b00000000000000000000000000011001 8!
b00000000000000000000000000000101 :!
b00000000000000000000000000010100 X!
#21
1#
b00000000000000000000000000011001 >
b00000000000000000000000000000101 ?
1O
b00000000000000000000000000011001 j
b00000000000000000000000000000101 k
15!
b00000000000000000000000000011001 H!
b00000000000000000000000000000101 J!
#22
0#
b00000000000000000000000000010001 &
b00000000000000000000000000001000 )
14
b00 8
b00 9
b00000000000000000000000000010001 L
b00000000000000000000000000001000 M
0O
b00000000000000000000000000010001 R
b00000000000000000000000000001000 U
1`
b00 d
b00 e
b00000000000000000000000000010001 x
b00000000000000000000000000001000 y
b00000000000000000000000000010001 {
b00000000000000000000000000000000 |
b00000000000000000000000000010001 }
b00000000000000000000000000001000 ~
b00000000000000000000000000010000 $!
b00000000000000000000000000010000 &!
b00000000000000000000000000010001 '!
b00000000000000000000000000001000 (!
b00000000000000000000000000010001 ,!
b00000000000000000000000000000000 -!
b00000000000000000000000000001000 /!
b00000000000000000000000000010000 4!
05!
b00000000000000000000000000000000 :!
b00000000000000000000000000010000 ;!
b00000000000000000000000000010000 <!
b00000000000000000000000000010001 X!
b00000000000000000000000000001000 Y!
b00000000000000000000000000010000 ]!
#23
1#
b00000000000000000000000000000000 ?
b00000000000000000000000000010000 C
b00000000000000000000000000010000 D
1O
b00000000000000000000000000000000 k
b00000000000000000000000000010000 o
b00000000000000000000000000010000 p
15!
b00000000000000000000000000000000 J!
b00000000000000000000000000010000 N!
b00000000000000000000000000010000 O!
#24
0#
b00000000000000000000000000000001 &
04
b10 9
b00000000000000000000000001001101 :
b00000000000000000000000000000001 L
b00000000000000000000000001001101 M
0O
b00000000000000000000000000000001 R
0`
b10 e
b00000000000000000000000001001101 f
b00000000000000000000000000000001 x
b00000000000000000000000001001101 y
b00000000000000000000000000000001 {
b00000000000000000000000001001101 |
b00000000000000000000000000000001 }
b00000000000000000000000001001101 ~
b00000000000000000000000001001110 !!
b00000000000000000000000000000001 '!
b00000000000000000000000001001101 (!
b00000000000000000000000001001110 *!
b00000000000000000000000000000001 ,!
b00000000000000000000000001001101 -!
05!
b00000000000000000000000001001110 8!
b00000000000000000000000001001101 :!
b00000000000000000000000000000001 X!
#25
1#
b00000000000000000000000001001110 >
b00000000000000000000000001001101 ?
1O
b00000000000000000000000001001110 j
b00000000000000000000000001001101 k
15!
b00000000000000000000000001001110 H!
b00000000000000000000000001001101 J!
