rtl/if_id_reg.v
// Description: IF/ID pipeline register

module if_id_reg(
    input wire clk,
    input wire rst,
    input wire if_id_write,
    input wire if_id_flush,
    input wire [31:0] instr_in,
    input wire [31:0] pc_in,
    output reg [31:0] instr_out,
    output reg [31:0] pc_out
);

always @(posedge clk or posedge rst) begin
    if (rst) begin
        instr_out <= 32'b0; 
        pc_out <= 32'b0; 
    end else if (if_id_flush) begin
        instr_out <= 32'b0;
        pc_out <= 32'b0;
    end else if (if_id_write) begin
        instr_out <= instr_in; 
        pc_out <= pc_in; 
    end
end
    
endmodule

rtl/pc_logic.v
module pc_logic (
    input wire [31:0] current_pc,
    input wire [31:0] branch_target,
    input wire [31:0] jump_target,
    input wire jump,
    input wire branch_taken,
    output reg [31:0] next_pc

);

// increment the current PC by 4
wire [31:0] pc_4;
assign pc_4 = current_pc + 32'd4;

always @(*) begin
    if (jump) begin
        next_pc = jump_target;
    end else if (branch_taken) begin
        next_pc = branch_target; 
    end else begin
        next_pc = pc_4; 
    end
end

endmodule

rtl/pc.v
module pc (
    input wire clk,
    input wire rst,
    input wire pc_write,
    input wire [31:0] next_pc,
    output reg [31:0] current_pc
);

    always @(posedge clk or posedge rst) begin
        if (rst) begin
            current_pc <= 32'b0; 
        end else if (pc_write) begin
            current_pc <= next_pc; 
        end
    end
    
endmodule

rtl/instr_mem.v
module instr_mem (
    input wire [31:0] addr,
    output wire [31:0] instr

);

reg [31:0] memory [0:255]; // 1KB instruction memory (32-bit)

// Initialize the instruction memory with some instructions
initial begin
    memory[0]  = 32'h00000093; // addi x1, x0, 0      ; x1 = 0
    memory[1]  = 32'h00500113; // addi x2, x0, 5      ; x2 = 5
    memory[2]  = 32'h00a00193; // addi x3, x0, 10     ; x3 = 10
    memory[3]  = 32'h00218333; // add x6, x3, x2      ; x6 = 10 + 5 = 15

    // ---------- Forwarding Test ----------
    memory[4]  = 32'h006282b3; // add x5, x5, x6      ; x5 += x6 → should forward x6 (EX hazard)
    memory[5]  = 32'h0062a2b3; // add x5, x5, x6      ; x5 += x6 → should forward x6 (MEM hazard)

    // ---------- Jump Test ----------
    memory[6]  = 32'h004000ef; // jal x1, 4           ; jump to PC+4+4 = PC+8 = instr[8], x1 = PC+4

    memory[7]  = 32'h00000013; // nop                ; should be skipped due to jump
    memory[8]  = 32'h00108093; // addi x1, x1, 1      ; x1 = x1 + 1

    // ---------- Branch Test (BEQ taken) ----------
    memory[9]  = 32'h00310063; // beq x2, x3, +6      ; x2 = 5, x3 = 10 → not equal → skip
    memory[10] = 32'h00c00093; // addi x1, x0, 12     ; skipped if branch taken

    // Update x3 = 5 (match x2)
    memory[11] = 32'h00500193; // addi x3, x0, 5      ; x3 = 5
    memory[12] = 32'h00319063; // beq x2, x3, +6      ; x2 = 5, x3 = 5 → branch taken, skip next

    memory[13] = 32'h00d00093; // addi x1, x0, 13     ; skipped if branch taken
    memory[14] = 32'h00100113; // addi x2, x0, 1      ; executed regardless
end






assign instr = memory[addr[9:2]]; // Assuming 4-byte aligned addresses
    
endmodule

rtl/if_stage_pip.v
// Description: IF-stage pipeline initialization

module if_stage_pip (
    input wire clk,
    input wire rst,
    input wire pc_write,
    input wire if_id_write,
    input wire if_id_flush,
    input wire jump,
    input wire branch_taken,
    input wire [31:0] branch_target,
    input wire [31:0] jump_target,
    output wire [31:0] instr_out,
    output wire [31:0] pc_out
);

wire [31:0] current_pc;
wire [31:0] next_pc;
wire [31:0] instr;

instr_mem instruction_memory (
    .addr(current_pc),
    .instr(instr)
);

pc prog_counter (
    .clk(clk),
    .rst(rst),
    .pc_write(pc_write),
    .next_pc(next_pc),
    .current_pc(current_pc)
);

pc_logic pc_logic_unit (
    .current_pc(current_pc),
    .branch_target(branch_target),
    .jump_target(jump_target),
    .jump(jump),
    .branch_taken(branch_taken),
    .next_pc(next_pc)
);

if_id_reg ifid_register (
    .clk(clk),
    .rst(rst),
    .if_id_write(if_id_write),
    .if_id_flush(if_id_flush),
    .instr_in(instr),
    .pc_in(current_pc),
    .instr_out(instr_out),
    .pc_out(pc_out)

);
    
endmodule

vcd/if_stage.vcd
$version Generated by VerilatedVcd $end
$timescale 1ps $end
 $scope module TOP $end
  $var wire 1 # clk $end
  $var wire 1 $ rst $end
  $var wire 1 % pc_write $end
  $var wire 1 & if_id_write $end
  $var wire 1 ' if_id_flush $end
  $var wire 1 ( jump $end
  $var wire 1 ) branch_taken $end
  $var wire 32 * branch_target [31:0] $end
  $var wire 32 + jump_target [31:0] $end
  $var wire 32 , instr_out [31:0] $end
  $var wire 32 - pc_out [31:0] $end
  $scope module if_stage_pip $end
   $var wire 1 . clk $end
   $var wire 1 / rst $end
   $var wire 1 0 pc_write $end
   $var wire 1 1 if_id_write $end
   $var wire 1 2 if_id_flush $end
   $var wire 1 3 jump $end
   $var wire 1 4 branch_taken $end
   $var wire 32 5 branch_target [31:0] $end
   $var wire 32 6 jump_target [31:0] $end
   $var wire 32 7 instr_out [31:0] $end
   $var wire 32 8 pc_out [31:0] $end
   $var wire 32 9 current_pc [31:0] $end
   $var wire 32 : next_pc [31:0] $end
   $var wire 32 ; instr [31:0] $end
   $scope module ifid_register $end
    $var wire 1 < clk $end
    $var wire 1 = rst $end
    $var wire 1 > if_id_write $end
    $var wire 1 ? if_id_flush $end
    $var wire 32 @ instr_in [31:0] $end
    $var wire 32 A pc_in [31:0] $end
    $var wire 32 B instr_out [31:0] $end
    $var wire 32 C pc_out [31:0] $end
   $upscope $end
   $scope module instruction_memory $end
    $var wire 32 D addr [31:0] $end
    $var wire 32 E instr [31:0] $end
   $upscope $end
   $scope module pc_logic_unit $end
    $var wire 32 F current_pc [31:0] $end
    $var wire 32 G branch_target [31:0] $end
    $var wire 32 H jump_target [31:0] $end
    $var wire 1 I jump $end
    $var wire 1 J branch_taken $end
    $var wire 32 K next_pc [31:0] $end
    $var wire 32 L pc_4 [31:0] $end
   $upscope $end
   $scope module prog_counter $end
    $var wire 1 M clk $end
    $var wire 1 N rst $end
    $var wire 1 O pc_write $end
    $var wire 32 P next_pc [31:0] $end
    $var wire 32 Q current_pc [31:0] $end
   $upscope $end
  $upscope $end
 $upscope $end
$enddefinitions $end


#0
0#
1$
0%
0&
0'
0(
0)
b00000000000000000000000000000000 *
b00000000000000000000000000000000 +
b00000000000000000000000000000000 ,
b00000000000000000000000000000000 -
0.
1/
00
01
02
03
04
b00000000000000000000000000000000 5
b00000000000000000000000000000000 6
b00000000000000000000000000000000 7
b00000000000000000000000000000000 8
b00000000000000000000000000000000 9
b00000000000000000000000000000100 :
b00000000000100000000000010010011 ;
0<
1=
0>
0?
b00000000000100000000000010010011 @
b00000000000000000000000000000000 A
b00000000000000000000000000000000 B
b00000000000000000000000000000000 C
b00000000000000000000000000000000 D
b00000000000100000000000010010011 E
b00000000000000000000000000000000 F
b00000000000000000000000000000000 G
b00000000000000000000000000000000 H
0I
0J
b00000000000000000000000000000100 K
b00000000000000000000000000000100 L
0M
1N
0O
b00000000000000000000000000000100 P
b00000000000000000000000000000000 Q
#5
1#
1.
1<
1M
#10
0#
0.
0<
0M
#15
1#
1.
1<
1M
#20
0#
0$
1%
1&
0.
0/
10
11
0<
0=
1>
0M
0N
1O
#25
1#
b00000000000100000000000010010011 ,
1.
b00000000000100000000000010010011 7
b00000000000000000000000000000100 9
b00000000000000000000000000001000 :
b00000000001000000000000100010011 ;
1<
b00000000001000000000000100010011 @
b00000000000000000000000000000100 A
b00000000000100000000000010010011 B
b00000000000000000000000000000100 D
b00000000001000000000000100010011 E
b00000000000000000000000000000100 F
b00000000000000000000000000001000 K
b00000000000000000000000000001000 L
1M
b00000000000000000000000000001000 P
b00000000000000000000000000000100 Q
#30
0#
0.
0<
0M
#35
1#
b00000000001000000000000100010011 ,
b00000000000000000000000000000100 -
1.
b00000000001000000000000100010011 7
b00000000000000000000000000000100 8
b00000000000000000000000000001000 9
b00000000000000000000000000001100 :
b00000000001100000000000110010011 ;
1<
b00000000001100000000000110010011 @
b00000000000000000000000000001000 A
b00000000001000000000000100010011 B
b00000000000000000000000000000100 C
b00000000000000000000000000001000 D
b00000000001100000000000110010011 E
b00000000000000000000000000001000 F
b00000000000000000000000000001100 K
b00000000000000000000000000001100 L
1M
b00000000000000000000000000001100 P
b00000000000000000000000000001000 Q
#40
0#
0.
0<
0M
#45
1#
b00000000001100000000000110010011 ,
b00000000000000000000000000001000 -
1.
b00000000001100000000000110010011 7
b00000000000000000000000000001000 8
b00000000000000000000000000001100 9
b00000000000000000000000000010000 :
b00000000010000000000001000010011 ;
1<
b00000000010000000000001000010011 @
b00000000000000000000000000001100 A
b00000000001100000000000110010011 B
b00000000000000000000000000001000 C
b00000000000000000000000000001100 D
b00000000010000000000001000010011 E
b00000000000000000000000000001100 F
b00000000000000000000000000010000 K
b00000000000000000000000000010000 L
1M
b00000000000000000000000000010000 P
b00000000000000000000000000001100 Q
#50
0#
0.
0<
0M
#55
1#
b00000000010000000000001000010011 ,
b00000000000000000000000000001100 -
1.
b00000000010000000000001000010011 7
b00000000000000000000000000001100 8
b00000000000000000000000000010000 9
b00000000000000000000000000010100 :
b00000000001000001000001010110011 ;
1<
b00000000001000001000001010110011 @
b00000000000000000000000000010000 A
b00000000010000000000001000010011 B
b00000000000000000000000000001100 C
b00000000000000000000000000010000 D
b00000000001000001000001010110011 E
b00000000000000000000000000010000 F
b00000000000000000000000000010100 K
b00000000000000000000000000010100 L
1M
b00000000000000000000000000010100 P
b00000000000000000000000000010000 Q
#60
0#
0.
0<
0M
#65
1#
b00000000001000001000001010110011 ,
b00000000000000000000000000010000 -
1.
b00000000001000001000001010110011 7
b00000000000000000000000000010000 8
b00000000000000000000000000010100 9
b00000000000000000000000000011000 :
b01000000001000101000001100110011 ;
1<
b01000000001000101000001100110011 @
b00000000000000000000000000010100 A
b00000000001000001000001010110011 B
b00000000000000000000000000010000 C
b00000000000000000000000000010100 D
b01000000001000101000001100110011 E
b00000000000000000000000000010100 F
b00000000000000000000000000011000 K
b00000000000000000000000000011000 L
1M
b00000000000000000000000000011000 P
b00000000000000000000000000010100 Q
#70
0#
0.
0<
0M
#75
1#
b01000000001000101000001100110011 ,
b00000000000000000000000000010100 -
1.
b01000000001000101000001100110011 7
b00000000000000000000000000010100 8
b00000000000000000000000000011000 9
b00000000000000000000000000011100 :
b00000000010000101111001110110011 ;
1<
b00000000010000101111001110110011 @
b00000000000000000000000000011000 A
b01000000001000101000001100110011 B
b00000000000000000000000000010100 C
b00000000000000000000000000011000 D
b00000000010000101111001110110011 E
b00000000000000000000000000011000 F
b00000000000000000000000000011100 K
b00000000000000000000000000011100 L
1M
b00000000000000000000000000011100 P
b00000000000000000000000000011000 Q
#80
0#
0.
0<
0M
#85
1#
b00000000010000101111001110110011 ,
b00000000000000000000000000011000 -
1.
b00000000010000101111001110110011 7
b00000000000000000000000000011000 8
b00000000000000000000000000011100 9
b00000000000000000000000000100000 :
b00000000010100101110010000110011 ;
1<
b00000000010100101110010000110011 @
b00000000000000000000000000011100 A
b00000000010000101111001110110011 B
b00000000000000000000000000011000 C
b00000000000000000000000000011100 D
b00000000010100101110010000110011 E
b00000000000000000000000000011100 F
b00000000000000000000000000100000 K
b00000000000000000000000000100000 L
1M
b00000000000000000000000000100000 P
b00000000000000000000000000011100 Q
#90
0#
0.
0<
0M
#95
1#
b00000000010100101110010000110011 ,
b00000000000000000000000000011100 -
1.
b00000000010100101110010000110011 7
b00000000000000000000000000011100 8
b00000000000000000000000000100000 9
b00000000000000000000000000100100 :
b00000000011000101100010010110011 ;
1<
b00000000011000101100010010110011 @
b00000000000000000000000000100000 A
b00000000010100101110010000110011 B
b00000000000000000000000000011100 C
b00000000000000000000000000100000 D
b00000000011000101100010010110011 E
b00000000000000000000000000100000 F
b00000000000000000000000000100100 K
b00000000000000000000000000100100 L
1M
b00000000000000000000000000100100 P
b00000000000000000000000000100000 Q
#100
0#
0.
0<
0M
#105
1#
b00000000011000101100010010110011 ,
b00000000000000000000000000100000 -
1.
b00000000011000101100010010110011 7
b00000000000000000000000000100000 8
b00000000000000000000000000100100 9
b00000000000000000000000000101000 :
b00000000011100101001010000110011 ;
1<
b00000000011100101001010000110011 @
b00000000000000000000000000100100 A
b00000000011000101100010010110011 B
b00000000000000000000000000100000 C
b00000000000000000000000000100100 D
b00000000011100101001010000110011 E
b00000000000000000000000000100100 F
b00000000000000000000000000101000 K
b00000000000000000000000000101000 L
1M
b00000000000000000000000000101000 P
b00000000000000000000000000100100 Q
#110
0#
0.
0<
0M
#115
1#
b00000000011100101001010000110011 ,
b00000000000000000000000000100100 -
1.
b00000000011100101001010000110011 7
b00000000000000000000000000100100 8
b00000000000000000000000000101000 9
b00000000000000000000000000101100 :
b00000000100000101101010010110011 ;
1<
b00000000100000101101010010110011 @
b00000000000000000000000000101000 A
b00000000011100101001010000110011 B
b00000000000000000000000000100100 C
b00000000000000000000000000101000 D
b00000000100000101101010010110011 E
b00000000000000000000000000101000 F
b00000000000000000000000000101100 K
b00000000000000000000000000101100 L
1M
b00000000000000000000000000101100 P
b00000000000000000000000000101000 Q
#120
0#
0.
0<
0M
#125
1#
b00000000100000101101010010110011 ,
b00000000000000000000000000101000 -
1.
b00000000100000101101010010110011 7
b00000000000000000000000000101000 8
b00000000000000000000000000101100 9
b00000000000000000000000000110000 :
b01000000101000101101010100110011 ;
1<
b01000000101000101101010100110011 @
b00000000000000000000000000101100 A
b00000000100000101101010010110011 B
b00000000000000000000000000101000 C
b00000000000000000000000000101100 D
b01000000101000101101010100110011 E
b00000000000000000000000000101100 F
b00000000000000000000000000110000 K
b00000000000000000000000000110000 L
1M
b00000000000000000000000000110000 P
b00000000000000000000000000101100 Q
#130
0#
0.
0<
0M
#135
1#
b01000000101000101101010100110011 ,
b00000000000000000000000000101100 -
1.
b01000000101000101101010100110011 7
b00000000000000000000000000101100 8
b00000000000000000000000000110000 9
b00000000000000000000000000110100 :
b00000000101100101010010110110011 ;
1<
b00000000101100101010010110110011 @
b00000000000000000000000000110000 A
b01000000101000101101010100110011 B
b00000000000000000000000000101100 C
b00000000000000000000000000110000 D
b00000000101100101010010110110011 E
b00000000000000000000000000110000 F
b00000000000000000000000000110100 K
b00000000000000000000000000110100 L
1M
b00000000000000000000000000110100 P
b00000000000000000000000000110000 Q
#140
0#
0.
0<
0M
#145
1#
b00000000101100101010010110110011 ,
b00000000000000000000000000110000 -
1.
b00000000101100101010010110110011 7
b00000000000000000000000000110000 8
b00000000000000000000000000110100 9
b00000000000000000000000000111000 :
b00000000110000101011011000110011 ;
1<
b00000000110000101011011000110011 @
b00000000000000000000000000110100 A
b00000000101100101010010110110011 B
b00000000000000000000000000110000 C
b00000000000000000000000000110100 D
b00000000110000101011011000110011 E
b00000000000000000000000000110100 F
b00000000000000000000000000111000 K
b00000000000000000000000000111000 L
1M
b00000000000000000000000000111000 P
b00000000000000000000000000110100 Q
#150
0#
0.
0<
0M
#155
1#
b00000000110000101011011000110011 ,
b00000000000000000000000000110100 -
1.
b00000000110000101011011000110011 7
b00000000000000000000000000110100 8
b00000000000000000000000000111000 9
b00000000000000000000000000111100 :
b00000000000100001010011010010011 ;
1<
b00000000000100001010011010010011 @
b00000000000000000000000000111000 A
b00000000110000101011011000110011 B
b00000000000000000000000000110100 C
b00000000000000000000000000111000 D
b00000000000100001010011010010011 E
b00000000000000000000000000111000 F
b00000000000000000000000000111100 K
b00000000000000000000000000111100 L
1M
b00000000000000000000000000111100 P
b00000000000000000000000000111000 Q
#160
0#
1)
b00000000000000000000000001000000 *
0.
14
b00000000000000000000000001000000 5
b00000000000000000000000001000000 :
0<
b00000000000000000000000001000000 G
1J
b00000000000000000000000001000000 K
0M
b00000000000000000000000001000000 P
#165
1#
b00000000000100001010011010010011 ,
b00000000000000000000000000111000 -
1.
b00000000000100001010011010010011 7
b00000000000000000000000000111000 8
b00000000000000000000000001000000 9
b00000000000100001100011110010011 ;
1<
b00000000000100001100011110010011 @
b00000000000000000000000001000000 A
b00000000000100001010011010010011 B
b00000000000000000000000000111000 C
b00000000000000000000000001000000 D
b00000000000100001100011110010011 E
b00000000000000000000000001000000 F
b00000000000000000000000001000100 L
1M
b00000000000000000000000001000000 Q
#170
0#
1(
0)
b00000000000000000000000001010000 +
0.
13
04
b00000000000000000000000001010000 6
b00000000000000000000000001010000 :
0<
b00000000000000000000000001010000 H
1I
0J
b00000000000000000000000001010000 K
0M
b00000000000000000000000001010000 P
#175
1#
b00000000000100001100011110010011 ,
b00000000000000000000000001000000 -
1.
b00000000000100001100011110010011 7
b00000000000000000000000001000000 8
b00000000000000000000000001010000 9
b00000000000100001101011010010011 ;
1<
b00000000000100001101011010010011 @
b00000000000000000000000001010000 A
b00000000000100001100011110010011 B
b00000000000000000000000001000000 C
b00000000000000000000000001010000 D
b00000000000100001101011010010011 E
b00000000000000000000000001010000 F
b00000000000000000000000001010100 L
1M
b00000000000000000000000001010000 Q
#180
0#
0%
0(
0.
00
03
b00000000000000000000000001010100 :
0<
0I
b00000000000000000000000001010100 K
0M
0O
b00000000000000000000000001010100 P
#185
1#
b00000000000100001101011010010011 ,
b00000000000000000000000001010000 -
1.
b00000000000100001101011010010011 7
b00000000000000000000000001010000 8
1<
b00000000000100001101011010010011 B
b00000000000000000000000001010000 C
1M
#190
0#
1%
1'
0.
10
12
0<
1?
0M
1O
#195
1#
b00000000000000000000000000000000 ,
b00000000000000000000000000000000 -
1.
b00000000000000000000000000000000 7
b00000000000000000000000000000000 8
b00000000000000000000000001010100 9
b00000000000000000000000001011000 :
b01000000000100001101011100010011 ;
1<
b01000000000100001101011100010011 @
b00000000000000000000000001010100 A
b00000000000000000000000000000000 B
b00000000000000000000000000000000 C
b00000000000000000000000001010100 D
b01000000000100001101011100010011 E
b00000000000000000000000001010100 F
b00000000000000000000000001011000 K
b00000000000000000000000001011000 L
1M
b00000000000000000000000001011000 P
b00000000000000000000000001010100 Q
#200
0#
0'
0.
02
0<
0?
0M
#205
1#
b01000000000100001101011100010011 ,
b00000000000000000000000001010100 -
1.
b01000000000100001101011100010011 7
b00000000000000000000000001010100 8
b00000000000000000000000001011000 9
b00000000000000000000000001011100 :
b00000000000000000000000000000000 ;
1<
b00000000000000000000000000000000 @
b00000000000000000000000001011000 A
b01000000000100001101011100010011 B
b00000000000000000000000001010100 C
b00000000000000000000000001011000 D
b00000000000000000000000000000000 E
b00000000000000000000000001011000 F
b00000000000000000000000001011100 K
b00000000000000000000000001011100 L
1M
b00000000000000000000000001011100 P
b00000000000000000000000001011000 Q
#210
0#
0.
0<
0M
#215
1#
b00000000000000000000000000000000 ,
b00000000000000000000000001011000 -
1.
b00000000000000000000000000000000 7
b00000000000000000000000001011000 8
b00000000000000000000000001011100 9
b00000000000000000000000001100000 :
1<
b00000000000000000000000001011100 A
b00000000000000000000000000000000 B
b00000000000000000000000001011000 C
b00000000000000000000000001011100 D
b00000000000000000000000001011100 F
b00000000000000000000000001100000 K
b00000000000000000000000001100000 L
1M
b00000000000000000000000001100000 P
b00000000000000000000000001011100 Q
#220
0#
0.
0<
0M
#225
1#
b00000000000000000000000001011100 -
1.
b00000000000000000000000001011100 8
b00000000000000000000000001100000 9
b00000000000000000000000001100100 :
1<
b00000000000000000000000001100000 A
b00000000000000000000000001011100 C
b00000000000000000000000001100000 D
b00000000000000000000000001100000 F
b00000000000000000000000001100100 K
b00000000000000000000000001100100 L
1M
b00000000000000000000000001100100 P
b00000000000000000000000001100000 Q
#230
0#
0.
0<
0M
#235
1#
b00000000000000000000000001100000 -
1.
b00000000000000000000000001100000 8
b00000000000000000000000001100100 9
b00000000000000000000000001101000 :
1<
b00000000000000000000000001100100 A
b00000000000000000000000001100000 C
b00000000000000000000000001100100 D
b00000000000000000000000001100100 F
b00000000000000000000000001101000 K
b00000000000000000000000001101000 L
1M
b00000000000000000000000001101000 P
b00000000000000000000000001100100 Q
