rtl/mem_wb_reg.v
module mem_wb_reg (
    input wire clk,
    input wire rst,
    input wire reg_write_in,
    input wire mem_to_reg_in,
    input wire [1:0] wb_sel_in,
    input wire [31:0] pc_in,
    input wire [31:0] alu_result_in,
    input wire [31:0] mem_data_in,
    input wire [4:0] rd_in,

    output reg [31:0] pc_out,
    output reg [31:0] alu_result_out,
    output reg [31:0] mem_data_out,
    output reg [4:0] rd_out,
    output reg [1:0] wb_sel_out,
    output reg reg_write_out,
    output reg mem_to_reg_out

);

always @(posedge clk or posedge rst) begin
    if (rst) begin
        reg_write_out <= 1'b0;
        mem_to_reg_out <= 1'b0;
        wb_sel_out <= 2'b0;
        pc_out <= 32'b0;
        alu_result_out <= 32'b0;
        mem_data_out <= 32'b0;
        rd_out <= 5'b0;

    end else begin
        reg_write_out <= reg_write_in;
        mem_to_reg_out <= mem_to_reg_in;
        wb_sel_out <= wb_sel_in;
        alu_result_out <= alu_result_in;
        pc_out <= pc_in;
        mem_data_out <= mem_data_in;
        rd_out <= rd_in;
    end
end

endmodule

rtl/mem_mux.v
// Description: Memory multiplexer for RISC-V load instructions
// Assumes aligned memory access (RV32I)

module mem_mux (
    input wire [31:0] mem_data,
    input wire [1:0] addr_lsb,
    input wire [2:0] funct3,
    output reg [31:0] mem_out
);

always @(*) begin 
        case (funct3) 
            3'b000: begin // lb
                case (addr_lsb)
                    2'b00: mem_out = {{24{mem_data[7]}}, mem_data[7:0]}; // 0th byte
                    2'b01: mem_out = {{24{mem_data[15]}}, mem_data[15:8]}; // 1st byte
                    2'b10: mem_out = {{24{mem_data[23]}}, mem_data[23:16]}; // 2nd byte
                    2'b11: mem_out = {{24{mem_data[31]}}, mem_data[31:24]}; // 3rd byte
                    default: mem_out = 32'b0;
                endcase
            end

            3'b001: begin // lh
                case (addr_lsb)
                    2'b00: mem_out = {{16{mem_data[15]}}, mem_data[15:0]}; // 0th and 1st bytes
                    2'b10: mem_out = {{16{mem_data[31]}}, mem_data[31:16]}; // 2nd and 3rd bytes
                    default: mem_out = 32'b0;
                endcase
            end

            3'b010: begin // lw
                mem_out = mem_data; 
            end

            3'b100: begin // lbu
                case (addr_lsb)
                    2'b00: mem_out = {24'b0, mem_data[7:0]}; // 0th byte
                    2'b01: mem_out = {24'b0, mem_data[15:8]}; // 1st byte
                    2'b10: mem_out = {24'b0, mem_data[23:16]}; // 2nd byte
                    2'b11: mem_out = {24'b0, mem_data[31:24]}; // 3rd byte
                    default: mem_out = 32'b0;
                endcase
            end

            3'b101: begin // lhu
                case (addr_lsb)
                    2'b00: mem_out = {16'b0, mem_data[15:0]}; // 0th and 1st bytes
                    2'b10: mem_out = {16'b0, mem_data[31:16]}; // 2nd and 3rd bytes
                    default: mem_out = 32'b0;
                endcase
            end

            default: mem_out = 32'b0; //invalid funct3
        
        endcase
end

endmodule

rtl/byte_logic.v
module byte_logic (
input wire [2:0] funct3,
input wire [1:0] addr_lsb,
output reg [3:0] byte_enable

);

always @(*) begin 
      case (funct3)
            3'b000: begin // sb
               case (addr_lsb)
                  2'b00: byte_enable = 4'b0001; // 0th byte
                  2'b01: byte_enable = 4'b0010; // 1st byte
                  2'b10: byte_enable = 4'b0100; // 2nd byte
                  2'b11: byte_enable = 4'b1000; // 3rd byte
                  default: byte_enable = 4'b0000;
               endcase
            end
            3'b001: begin // sh
               case (addr_lsb)
                  2'b00: byte_enable = 4'b0011; // 0th and 1st bytes
                  2'b10: byte_enable = 4'b1100; // 2nd and 3rd bytes
                  default: byte_enable = 4'b0000;
               endcase
            end
            3'b010: begin // sw
               byte_enable = 4'b1111; // all bytes
            end

            default: byte_enable = 4'b0000; // invalid funct3
      endcase
end

endmodule

rtl/data_mem.v
module data_mem (

    input wire clk,
    input wire [31:0] addr,
    input wire [31:0] write_data,
    input [3:0] byte_enable,
    input wire mem_write,
    input wire mem_read,
    output reg [31:0] read_data

);

reg [31:0] mem [0:1023];

always @(posedge clk) begin
    if (mem_write) begin
        if (byte_enable[0]) mem[addr[11:2]][7:0] <= write_data[7:0];
        if (byte_enable[1]) mem[addr[11:2]][15:8] <= write_data[15:8];
        if (byte_enable[2]) mem[addr[11:2]][23:16] <= write_data[23:16];
        if (byte_enable[3]) mem[addr[11:2]][31:24] <= write_data[31:24];
    end
end

always @(posedge clk) begin
    if (mem_read) begin
        read_data <= mem[addr[11:2]];
    end else begin
        read_data <= 32'b0; 
    end
end

endmodule

rtl/mem_stage_pip.v
module mem_stage_pip(
    input wire clk,
    input wire rst,
    input wire [31:0] pc_in,
    input wire [31:0] alu_result_in,
    input wire [31:0] rs2_data_in,
    input wire [2:0] funct3_in,
    input wire [4:0] rd_in,
    input wire [1:0] wb_sel_in,
    input wire mem_read_in,
    input wire mem_write_in,
    input wire reg_write_in,
    input wire mem_to_reg_in,

    output wire [31:0] pc_out,
    output wire [31:0] alu_result_out,
    output wire [31:0] mem_data_out,
    output wire [4:0] rd_out,
    output wire [1:0] wb_sel_out,
    output wire reg_write_out,
    output wire mem_to_reg_out

);
wire [1:0] addr_lsb;
wire [3:0] byte_enable; 
wire [31:0] mem_data;
wire [31:0] read_data;

assign addr_lsb = alu_result_in[1:0]; 

data_mem memory (
    .clk(clk),
    .addr(alu_result_in),
    .write_data(rs2_data_in),
    .byte_enable(byte_enable),
    .mem_write(mem_write_in),
    .mem_read(mem_read_in),
    .read_data(read_data)

);

byte_logic byte_mask (
    .funct3(funct3_in),
    .addr_lsb(addr_lsb),
    .byte_enable(byte_enable)

);

mem_mux mem_access (
    .mem_data(read_data),
    .addr_lsb(addr_lsb),
    .funct3(funct3_in),
    .mem_out(mem_data)
);

mem_wb_reg memwb_register (
    .clk(clk),
    .rst(rst),
    .reg_write_in(reg_write_in),
    .mem_to_reg_in(mem_to_reg_in),
    .alu_result_in(alu_result_in),
    .pc_in(pc_in),
    .mem_data_in(mem_data),
    .rd_in(rd_in),
    .wb_sel_in(wb_sel_in),
    .reg_write_out(reg_write_out),
    .mem_to_reg_out(mem_to_reg_out),
    .wb_sel_out(wb_sel_out),
    .pc_out(pc_out),   
    .alu_result_out(alu_result_out),
    .mem_data_out(mem_data_out),
    .rd_out(rd_out)
);





endmodule

vcd/mem_stage.vcd
$version Generated by VerilatedVcd $end
$timescale 1ps $end
 $scope module TOP $end
  $var wire 1 # clk $end
  $var wire 1 $ rst $end
  $var wire 32 % pc_in [31:0] $end
  $var wire 32 & alu_result_in [31:0] $end
  $var wire 32 ' rs2_data_in [31:0] $end
  $var wire 3 ( funct3_in [2:0] $end
  $var wire 5 ) rd_in [4:0] $end
  $var wire 2 * wb_sel_in [1:0] $end
  $var wire 1 + mem_read_in $end
  $var wire 1 , mem_write_in $end
  $var wire 1 - reg_write_in $end
  $var wire 1 . mem_to_reg_in $end
  $var wire 32 / pc_out [31:0] $end
  $var wire 32 0 alu_result_out [31:0] $end
  $var wire 32 1 mem_data_out [31:0] $end
  $var wire 5 2 rd_out [4:0] $end
  $var wire 2 3 wb_sel_out [1:0] $end
  $var wire 1 4 reg_write_out $end
  $var wire 1 5 mem_to_reg_out $end
  $scope module mem_stage_pip $end
   $var wire 1 6 clk $end
   $var wire 1 7 rst $end
   $var wire 32 8 pc_in [31:0] $end
   $var wire 32 9 alu_result_in [31:0] $end
   $var wire 32 : rs2_data_in [31:0] $end
   $var wire 3 ; funct3_in [2:0] $end
   $var wire 5 < rd_in [4:0] $end
   $var wire 2 = wb_sel_in [1:0] $end
   $var wire 1 > mem_read_in $end
   $var wire 1 ? mem_write_in $end
   $var wire 1 @ reg_write_in $end
   $var wire 1 A mem_to_reg_in $end
   $var wire 32 B pc_out [31:0] $end
   $var wire 32 C alu_result_out [31:0] $end
   $var wire 32 D mem_data_out [31:0] $end
   $var wire 5 E rd_out [4:0] $end
   $var wire 2 F wb_sel_out [1:0] $end
   $var wire 1 G reg_write_out $end
   $var wire 1 H mem_to_reg_out $end
   $var wire 2 I addr_lsb [1:0] $end
   $var wire 4 J byte_enable [3:0] $end
   $var wire 32 K mem_data [31:0] $end
   $var wire 32 L read_data [31:0] $end
   $scope module byte_mask $end
    $var wire 3 M funct3 [2:0] $end
    $var wire 2 N addr_lsb [1:0] $end
    $var wire 4 O byte_enable [3:0] $end
   $upscope $end
   $scope module mem_access $end
    $var wire 32 P mem_data [31:0] $end
    $var wire 2 Q addr_lsb [1:0] $end
    $var wire 3 R funct3 [2:0] $end
    $var wire 32 S mem_out [31:0] $end
   $upscope $end
   $scope module memory $end
    $var wire 1 T clk $end
    $var wire 32 U addr [31:0] $end
    $var wire 32 V write_data [31:0] $end
    $var wire 4 W byte_enable [3:0] $end
    $var wire 1 X mem_write $end
    $var wire 1 Y mem_read $end
    $var wire 32 Z read_data [31:0] $end
   $upscope $end
   $scope module memwb_register $end
    $var wire 1 [ clk $end
    $var wire 1 \ rst $end
    $var wire 1 ] reg_write_in $end
    $var wire 1 ^ mem_to_reg_in $end
    $var wire 2 _ wb_sel_in [1:0] $end
    $var wire 32 ` pc_in [31:0] $end
    $var wire 32 a alu_result_in [31:0] $end
    $var wire 32 b mem_data_in [31:0] $end
    $var wire 5 c rd_in [4:0] $end
    $var wire 32 d pc_out [31:0] $end
    $var wire 32 e alu_result_out [31:0] $end
    $var wire 32 f mem_data_out [31:0] $end
    $var wire 5 g rd_out [4:0] $end
    $var wire 2 h wb_sel_out [1:0] $end
    $var wire 1 i reg_write_out $end
    $var wire 1 j mem_to_reg_out $end
   $upscope $end
  $upscope $end
 $upscope $end
$enddefinitions $end


#0
0#
1$
b00000000000000000000000000000000 %
b00000000000000000000000000000000 &
b00000000000000000000000000000000 '
b000 (
b00000 )
b00 *
0+
0,
0-
0.
b00000000000000000000000000000000 /
b00000000000000000000000000000000 0
b00000000000000000000000000000000 1
b00000 2
b00 3
04
05
06
17
b00000000000000000000000000000000 8
b00000000000000000000000000000000 9
b00000000000000000000000000000000 :
b000 ;
b00000 <
b00 =
0>
0?
0@
0A
b00000000000000000000000000000000 B
b00000000000000000000000000000000 C
b00000000000000000000000000000000 D
b00000 E
b00 F
0G
0H
b00 I
b0001 J
b00000000000000000000000000000000 K
b00000000000000000000000000000000 L
b000 M
b00 N
b0001 O
b00000000000000000000000000000000 P
b00 Q
b000 R
b00000000000000000000000000000000 S
0T
b00000000000000000000000000000000 U
b00000000000000000000000000000000 V
b0001 W
0X
0Y
b00000000000000000000000000000000 Z
0[
1\
0]
0^
b00 _
b00000000000000000000000000000000 `
b00000000000000000000000000000000 a
b00000000000000000000000000000000 b
b00000 c
b00000000000000000000000000000000 d
b00000000000000000000000000000000 e
b00000000000000000000000000000000 f
b00000 g
b00 h
0i
0j
#5
1#
16
1T
1[
#10
0#
06
0T
0[
#15
1#
16
1T
1[
#20
0#
0$
06
07
0T
0[
0\
#25
1#
16
1T
1[
#30
0#
b00000000000000000000000100000000 %
b00000000000000000000000000000100 &
b00010010001101000101011001111000 '
b010 (
1,
06
b00000000000000000000000100000000 8
b00000000000000000000000000000100 9
b00010010001101000101011001111000 :
b010 ;
1?
b1111 J
b010 M
b1111 O
b010 R
0T
b00000000000000000000000000000100 U
b00010010001101000101011001111000 V
b1111 W
1X
0[
b00000000000000000000000100000000 `
b00000000000000000000000000000100 a
#35
1#
b00000000000000000000000100000000 /
b00000000000000000000000000000100 0
16
b00000000000000000000000100000000 B
b00000000000000000000000000000100 C
1T
1[
b00000000000000000000000100000000 d
b00000000000000000000000000000100 e
#40
0#
b00000000000000000000000100000100 %
b00000000000000000000000000000000 '
b00001 )
b01 *
1+
0,
1-
1.
06
b00000000000000000000000100000100 8
b00000000000000000000000000000000 :
b00001 <
b01 =
1>
0?
1@
1A
0T
b00000000000000000000000000000000 V
0X
1Y
0[
1]
1^
b01 _
b00000000000000000000000100000100 `
b00001 c
#45
1#
b00000000000000000000000100000100 /
b00001 2
b01 3
14
15
16
b00000000000000000000000100000100 B
b00001 E
b01 F
1G
1H
b00010010001101000101011001111000 K
b00010010001101000101011001111000 L
b00010010001101000101011001111000 P
b00010010001101000101011001111000 S
1T
b00010010001101000101011001111000 Z
1[
b00010010001101000101011001111000 b
b00000000000000000000000100000100 d
b00001 g
b01 h
1i
1j
#50
0#
06
0T
0[
#55
1#
b00010010001101000101011001111000 1
16
b00010010001101000101011001111000 D
1T
1[
b00010010001101000101011001111000 f
#60
0#
b00000000000000000000000100001000 %
b00000000000000000000000000001000 &
b00000000000000000000000010101010 '
b000 (
b00000 )
b00 *
0+
1,
0-
0.
06
b00000000000000000000000100001000 8
b00000000000000000000000000001000 9
b00000000000000000000000010101010 :
b000 ;
b00000 <
b00 =
0>
1?
0@
0A
b0001 J
b00000000000000000000000001111000 K
b000 M
b0001 O
b000 R
b00000000000000000000000001111000 S
0T
b00000000000000000000000000001000 U
b00000000000000000000000010101010 V
b0001 W
1X
0Y
0[
0]
0^
b00 _
b00000000000000000000000100001000 `
b00000000000000000000000000001000 a
b00000000000000000000000001111000 b
b00000 c
#65
1#
b00000000000000000000000100001000 /
b00000000000000000000000000001000 0
b00000000000000000000000001111000 1
b00000 2
b00 3
04
05
16
b00000000000000000000000100001000 B
b00000000000000000000000000001000 C
b00000000000000000000000001111000 D
b00000 E
b00 F
0G
0H
b00000000000000000000000000000000 K
b00000000000000000000000000000000 L
b00000000000000000000000000000000 P
b00000000000000000000000000000000 S
1T
b00000000000000000000000000000000 Z
1[
b00000000000000000000000000000000 b
b00000000000000000000000100001000 d
b00000000000000000000000000001000 e
b00000000000000000000000001111000 f
b00000 g
b00 h
0i
0j
#70
0#
b00000000000000000000000100001100 %
b00000000000000000000000000000000 '
b00010 )
b01 *
1+
0,
1-
1.
06
b00000000000000000000000100001100 8
b00000000000000000000000000000000 :
b00010 <
b01 =
1>
0?
1@
1A
0T
b00000000000000000000000000000000 V
0X
1Y
0[
1]
1^
b01 _
b00000000000000000000000100001100 `
b00010 c
#75
1#
b00000000000000000000000100001100 /
b00000000000000000000000000000000 1
b00010 2
b01 3
14
15
16
b00000000000000000000000100001100 B
b00000000000000000000000000000000 D
b00010 E
b01 F
1G
1H
b11111111111111111111111110101010 K
b00000000000000000000000010101010 L
b00000000000000000000000010101010 P
b11111111111111111111111110101010 S
1T
b00000000000000000000000010101010 Z
1[
b11111111111111111111111110101010 b
b00000000000000000000000100001100 d
b00000000000000000000000000000000 f
b00010 g
b01 h
1i
1j
#80
0#
06
0T
0[
#85
1#
b11111111111111111111111110101010 1
16
b11111111111111111111111110101010 D
1T
1[
b11111111111111111111111110101010 f
